{
  "fdd_id": "637918-2025",
  "brand": "Burger King",
  "franchisor_legal_name": "Burger King Company LLC",
  "franchisor_state": "FL",
  "franchisor_address": "5707 Blue Lagoon Drive, Miami, Florida 33126",
  "franchisor_phone": "(305) 378-7128",
  "franchisor_website": "www.bk.com",
  "issuance_date": "2025-03-26",
  "amendment_date": "2026-01-16",
  "state_filed": "WI",
  "entity_type": "Florida limited liability company",
  "formation_date": "2022-02-04",
  "predecessor": "Burger King Corporation (1954-2022)",
  "parent_entity": "Restaurant Brands International Limited Partnership (Ontario)",
  "parent_general_partner": "Restaurant Brands International Inc. (Canadian corporation)",
  "parent_address": "130 King Street West, Suite 300, Toronto, Ontario M5X 1E1 Canada",
  "largest_voting_block": "3G Restaurant Brands Holdings LP (~26%)",
  "sister_brands": ["Tim Hortons", "Popeyes Louisiana Kitchen", "Firehouse Subs"],
  "business_description": "Quick-service restaurant specializing in sale of hamburgers under BURGER KING marks",
  "franchise_type": "Single-unit and multi-unit",
  "ownership_types": ["Individual/Owner-Operator", "Entity"],

  "system_size": {
    "as_of_date": "2024-12-31",
    "worldwide_total": 19732,
    "us_total": 6701,
    "us_franchised": 5524,
    "us_company_owned": 1177,
    "source_section": "Item 1, Item 20",
    "source_pages": [14, 112],
    "confidence": "high"
  },

  "franchise_fee": {
    "standard": 50000,
    "minimum": 15000,
    "term_basis": "20-year standard",
    "prorated": true,
    "refundable": false,
    "source_section": "Item 5",
    "source_pages": [29],
    "confidence": "high"
  },

  "royalty": {
    "rate": "4.5%",
    "basis": "monthly Gross Sales",
    "payment_schedule": "monthly, 10th of next month",
    "reduced_programs_available": true,
    "dip_year1_rate": "2.5%",
    "source_section": "Item 6",
    "source_pages": [34, 39],
    "confidence": "high"
  },

  "advertising_fee": {
    "rate": "up to 4.5%",
    "current_rate": "4.5%",
    "basis": "monthly Gross Sales",
    "payment_schedule": "monthly, 10th of next month",
    "minimum_working_media_pct": 65,
    "fund_audit_available": true,
    "source_section": "Item 6, Item 11",
    "source_pages": [34, 42, 70],
    "confidence": "high"
  },

  "investment_spending": {
    "rate": "up to 2.0%",
    "basis": "Gross Sales",
    "mandatory_if_majority": true,
    "majority_threshold": "66.7%",
    "source_section": "Item 6",
    "source_pages": [35],
    "confidence": "high"
  },

  "digital_services_fee": {
    "monthly_flat": 110,
    "pct_digital_sales": "1%",
    "annual_cap": 4500,
    "source_section": "Item 6",
    "source_pages": [36],
    "confidence": "high"
  },

  "initial_investment": {
    "traditional_low": 2049200,
    "traditional_high": 4705600,
    "indoor_mrs_low": 348400,
    "indoor_mrs_high": 789100,
    "excludes_real_estate": true,
    "source_section": "Item 7",
    "source_pages": [48, 49, 50, 51, 52],
    "confidence": "high"
  },

  "term": {
    "initial_years": 20,
    "non_traditional_may_be_less": true,
    "renewal_right": false,
    "successor_option": true,
    "successor_may_have_materially_different_terms": true,
    "successor_requires_general_release": true,
    "no_successor_for": ["Big-Box", "Delivery Restaurant"],
    "source_section": "Item 17",
    "source_pages": [82],
    "confidence": "high"
  },

  "territory": {
    "exclusive": false,
    "protected": false,
    "development_agreement_territory": true,
    "development_agreement_exclusive": false,
    "alternative_channels_reserved": true,
    "sister_brand_competition": true,
    "source_section": "Item 12",
    "source_pages": [72, 73, 74],
    "confidence": "high"
  },

  "noncompete": {
    "during_term": "No interest in any hamburger business",
    "post_term_duration": "1 year",
    "post_term_radius": "2 miles",
    "source_section": "Item 17",
    "source_pages": [87],
    "confidence": "high"
  },

  "dispute_resolution": {
    "venue": "U.S. District Court for S.D. Florida or Miami-Dade County state court",
    "governing_law": "Florida",
    "mediation": "mandatory non-binding for development disputes only",
    "arbitration": "none mandatory; voluntary for development disputes",
    "jury_waiver": "in certain agreements (Crown Your Career)",
    "source_section": "Item 17",
    "source_pages": [87],
    "confidence": "high"
  },

  "transfer": {
    "bkc_consent_required": true,
    "transfer_fee_first_restaurant": 2000,
    "transfer_fee_additional": 500,
    "right_of_first_refusal": true,
    "training_fee_on_transfer": 7500,
    "source_section": "Item 17",
    "source_pages": [85, 86],
    "confidence": "high"
  },

  "termination": {
    "cure_periods": {
      "5_days": "operational, quality, health/sanitation, unapproved products, abandonment, insurance",
      "10_days": "non-payment of royalty/advertising",
      "30_days": "late reports, unapproved equipment, maintenance/remodel failure, behavior, laws",
      "60_days": "failure to pay bills, other FA/lease defaults",
      "180_days": "failure to meet minimum financial criteria"
    },
    "non_curable": "bankruptcy, criminal conviction, unfair competition, false statements, gross sales understatement, failure to close for health/safety, unauthorized transfer, repeated breaches",
    "source_section": "Item 17",
    "source_pages": [83, 84],
    "confidence": "high"
  },

  "death_disability": {
    "heir_approval_required": true,
    "sale_deadline_months": 12,
    "bkc_may_operate_pending": true,
    "source_section": "Item 17",
    "source_pages": [86],
    "confidence": "high"
  },

  "training": {
    "program_name": "Burger King Franchisee Onboarding Training Program",
    "classroom_hours": "up to 20",
    "in_restaurant_hours": "up to 320",
    "location": "Miami, FL or designated locations; in Training Restaurants",
    "fee_per_trainee": 7500,
    "servsafe_required": true,
    "source_section": "Item 11",
    "source_pages": [66, 67],
    "confidence": "high"
  },

  "technology": {
    "pos_cost_low": 20000,
    "pos_cost_high": 25000,
    "network_monthly_low": 220,
    "network_monthly_high": 450,
    "data_reporting_annual_low": 200,
    "data_reporting_annual_high": 1200,
    "loyalty_program": "Royal Perks",
    "loyalty_mandatory": true,
    "free_guest_wifi_required": true,
    "source_section": "Item 11",
    "source_pages": [68, 69],
    "confidence": "high"
  },

  "supplier_restrictions": {
    "approved_supplier_required": true,
    "pct_establishment_costs_from_approved": "65-90%",
    "pct_operating_costs_from_approved": "30-60%",
    "bkc_sole_supplier_items": ["digital/loyalty platforms", "network services", "digital menu boards", "gift card services"],
    "purchasing_cooperative": "Restaurant Services Inc. (RSI)",
    "rsi_board_members": 21,
    "new_supplier_approval_time_days": "90-160",
    "supplier_rebates_to_ad_fund_pct": "8.4%",
    "bkc_revenue_from_franchisee_purchases_M": 227,
    "source_section": "Item 8",
    "source_pages": [55, 56, 57],
    "confidence": "high"
  },

  "item19": {
    "disclosure_type": "gross_sales_only",
    "no_cost_data": true,
    "no_ebitda": true,
    "period": "2024-01-01 to 2024-12-31",
    "traditional": {
      "total_in_system": 6229,
      "reporting_count": 5837,
      "franchised_count": 4774,
      "company_owned_count": 1063,
      "avg_sales_consolidated": 1671613,
      "median_sales_consolidated": 1579183,
      "avg_sales_franchised": 1658463,
      "median_sales_franchised": 1561502,
      "high_sales": 5833717,
      "low_sales": 271485,
      "pct_at_or_above_avg": 43
    },
    "non_traditional": {
      "total_in_system": 874,
      "reporting_count": 775,
      "avg_sales": 1321324,
      "median_sales": 1155563,
      "high_sales": 7387029,
      "low_sales": 208320,
      "pct_at_or_above_avg": 39
    },
    "remodel_uplift": {
      "sample_size": 893,
      "remodel_period": "Jan 2018 - Dec 2023",
      "min_capex": 650000,
      "full_remodel_avg_uplift_pct": 11.4,
      "scrape_rebuild_avg_uplift_pct": 26.1,
      "double_dt_conversion_avg_uplift_pct": 15.8,
      "year3_cumulative_avg_uplift_pct": 13.4
    },
    "source_section": "Item 19",
    "source_pages": [98, 99, 100, 101, 102, 103, 104, 105, 106, 107, 108, 109, 110, 111],
    "confidence": "high"
  },

  "item20": {
    "systemwide_trajectory": {
      "2022_total_end": 7042,
      "2023_total_end": 6778,
      "2024_total_end": 6701,
      "2024_franchised_end": 5524,
      "2024_company_owned_end": 1177
    },
    "2024_franchised_activity": {
      "opened": 63,
      "terminations": 0,
      "non_renewals": 49,
      "reacquired_by_franchisor": 1061,
      "ceased_other": 69
    },
    "projected_2025": {
      "new_franchised": 48,
      "new_company_owned": 2
    },
    "confidentiality_clause": true,
    "franchisee_association": "National Franchisee Association (NFA), Kennesaw, GA",
    "ceased_operations_count": 1433,
    "source_section": "Item 20",
    "source_pages": [112, 113, 114, 115, 116, 117, 118, 119, 120, 121, 122, 123, 124, 125, 126],
    "confidence": "high"
  },

  "item21": {
    "auditor": "not individually extracted from Exhibit Q",
    "financial_statements_entity": "RBI and RBILP (consolidated)",
    "periods_covered": "3 years ended Dec 31, 2024",
    "guarantor_certain_states": "RBILP (CA, IL, MD, ND, RI, VA, WA)",
    "guarantor_other_states": "RBI",
    "rbi_net_income_2024_M": 1445,
    "rbi_net_income_2023_M": 1718,
    "rbi_net_income_2022_M": 1482,
    "rbi_income_from_operations_2024_M": 2419,
    "bk_segment_income_2024_M": 410,
    "bk_segment_income_2023_M": 386,
    "bk_segment_income_2022_M": 396,
    "rbi_interest_expense_2024_M": 577,
    "us_long_lived_assets_2024_M": 2684,
    "us_long_lived_assets_2023_M": 1578,
    "source_section": "Item 21, Exhibit Q",
    "source_pages": [127, 850, 900],
    "confidence": "medium",
    "confidence_note": "Key figures sampled from Exhibit Q; full line-item extraction not performed"
  },

  "litigation_summary": {
    "pending_material": 8,
    "bkc_direct_party": 2,
    "rbi_affiliate_party": 6,
    "franchisor_initiated": 1,
    "concluded_material": 6,
    "largest_pending_claim": "$500M+ (FIF v. BK Corporation)",
    "source_section": "Item 3",
    "source_pages": [20, 21, 22, 23, 24, 25, 26, 27],
    "confidence": "high"
  },

  "bankruptcy": {
    "disclosed": false,
    "source_section": "Item 4",
    "source_pages": [28],
    "confidence": "high"
  },

  "public_figures": {
    "used": false,
    "source_section": "Item 18",
    "source_pages": [97],
    "confidence": "high"
  },

  "special_risks": [
    "Out-of-state dispute resolution (Florida)",
    "Mandatory non-binding mediation for development disputes before litigation"
  ],

  "state_addenda_states": ["CA", "HI", "IL", "IN", "MD", "MI", "MN", "NY", "ND", "RI", "SD", "VA", "WA", "WI"],

  "key_programs": [
    "2024 Multi-Unit New Development Incentive Program",
    "Crown Your Career Program (employee-to-franchisee)",
    "Carrols Refranchise Program",
    "Reclaim the Flame 2 Remodel Program",
    "Fuel the Flame Co-Investment Agreement",
    "Franchise Success System (FSS) grading"
  ],

  "red_flags": [
    "No exclusive territory — significant encroachment risk from own system and sister brands",
    "Successor franchise agreement may have materially different terms",
    "No cost/EBITDA data in Item 19 — gross sales only",
    "System shrinkage: net loss of 77 US restaurants in 2024 (and 264 in 2023)",
    "Massive Carrols reacquisition (1,061 restaurants in 2024) shifts balance toward company-owned",
    "Total fee burden potentially >11% before rent (royalty 4.5% + ad 4.5% + digital + IS)",
    "Confidentiality restrictions on former franchisee communications",
    "Cross-default clauses — default in any agreement triggers default in all others",
    "Florida venue and law for all disputes — disadvantageous for out-of-state franchisees",
    "No termination by franchisee provision — only 'as permitted by applicable state law'"
  ]
}
