{
  "extraction_date": "2026-04-15",
  "fdd_id": "637935-2025",
  "brand": "DQ Grill & Chill",
  "franchisor_legal_name": "American Dairy Queen Corporation",
  "franchisor_state_of_incorporation": "Delaware",
  "franchisor_year_incorporated": 1962,
  "franchisor_address": "8000 Tower, Suite 700, 8331 Norman Center Drive, Bloomington, MN 55437",
  "franchisor_phone": "(952) 830-0200",
  "franchisor_email": "development@idq.com",
  "franchisor_website": "www.dq.com",
  "parent_company": "International Dairy Queen, Inc. (IDQ)",
  "ultimate_parent": "Berkshire Hathaway, Inc.",
  "issuance_date": "March 27, 2025, as amended January 29, 2026",
  "state_filed": "Wisconsin (WI-DFI)",
  "pdf_pages": 512,
  "document_identity": {
    "source_section": "Cover Page",
    "source_pages": [1],
    "confidence": "high"
  },
  "concept_description": {
    "value": "Quick service food restaurant with indoor seating selling the full line of approved DQ soft-serve, treat, food and beverage menu items. Two prototypical freestanding buildings: Next Gen Core 34 (1,938 sq ft, seats 34) and Next Gen Core 46 (2,208 sq ft, seats 46). Street locations (freestanding/strip) and Captive-venue locations (malls, airports, campus, etc.).",
    "source_section": "Item 1",
    "source_pages": [9, 10],
    "confidence": "high"
  },
  "system_size": {
    "total_global": "over 7,700",
    "us_gc_direct_licensed": 1971,
    "us_gc_subfranchised": 567,
    "us_texas_dq": 568,
    "us_dq_treat": 727,
    "canada_gc": 510,
    "canada_treat": 184,
    "international": 2853,
    "company_owned_gc": 2,
    "as_of_date": "2024-12-31",
    "source_section": "Item 1, Item 20",
    "source_pages": [13, 14, 69],
    "confidence": "high"
  },
  "initial_franchise_fee": {
    "value": 45000,
    "currency": "USD",
    "non_refundable_deposit": 10000,
    "refund_conditions": "Withdrawal before construction; training failure; no site in 90 days; no construction in 180 days",
    "source_section": "Item 5",
    "source_pages": [20, 21],
    "confidence": "high"
  },
  "multi_unit_fee": {
    "trade_area_reservation_fee_per_unit": 22500,
    "credit_against_franchise_fee": true,
    "refundable": false,
    "source_section": "Item 5",
    "source_pages": [21],
    "confidence": "high"
  },
  "royalty": {
    "rate": "4% of Gross Sales",
    "payment_frequency": "Monthly, due 10th of next month",
    "source_section": "Item 6",
    "source_pages": [22],
    "confidence": "high"
  },
  "sales_promotion_fee": {
    "rate": "5%–6% of Gross Sales",
    "determination": "ADQ determines within range; 90 days advance notice of adjustment",
    "payment_frequency": "Monthly, due 10th of next month",
    "source_section": "Item 6",
    "source_pages": [22],
    "confidence": "high"
  },
  "total_ongoing_fee_load": {
    "value": "9%–10% of Gross Sales",
    "components": "4% royalty + 5%–6% sales promotion",
    "source_section": "Item 6",
    "source_pages": [22],
    "confidence": "high"
  },
  "transfer_fee": {
    "value": 6000,
    "escalation": "$500 increase every 5 years starting Jan 1, 2030",
    "source_section": "Item 6",
    "source_pages": [22],
    "confidence": "high"
  },
  "renewal_fee": {
    "value": 22500,
    "source_section": "Item 6",
    "source_pages": [22],
    "confidence": "high"
  },
  "termination_fee": {
    "formula": "2× continuing license fee for last 12 months of active operations; or 24× average monthly if <12 months; or remaining months × average if <24 months remain",
    "source_section": "Item 6",
    "source_pages": [23],
    "confidence": "high"
  },
  "initial_investment": {
    "low": 1516200,
    "high": 2543050,
    "excludes_land": true,
    "land_estimate_if_purchasing": "$250,000–$800,000",
    "source_section": "Item 7",
    "source_pages": [26, 27],
    "confidence": "high"
  },
  "territory": {
    "exclusive": false,
    "type": "Site-only franchise, no exclusive territory",
    "franchisor_competition_rights": "ADQ and affiliates may operate and franchise competing businesses at any location except the specific authorized location. May sell via internet, catalog, telemarketing, social media, mobile apps, third-party platforms without compensation.",
    "multi_unit_trade_area": "MultiTRA grants non-exclusive development right with designated trade areas, subject to ADQ carve-outs for large venues, institutional locations, and pre-existing commitments",
    "source_section": "Item 12",
    "source_pages": [49, 50],
    "confidence": "high"
  },
  "franchise_term": {
    "initial_years": 20,
    "renewal_terms": 1,
    "renewal_years": "Shorter of 10 years or remaining lease term",
    "renewal_conditions": "Sign then-current agreement (may differ materially); modernize; good standing; pay $22,500 renewal fee; sign release",
    "materially_different_risk": true,
    "source_section": "Item 17",
    "source_pages": [56],
    "confidence": "high"
  },
  "noncompete": {
    "during_term": "No involvement in quick-service restaurant serving hamburgers (without alcohol) or business generating >10% revenue from frozen treats (Competitive Business)",
    "post_term": "500 meters from authorized location for 1 year (Street); same building/venue (Captive-venue)",
    "source_section": "Item 17",
    "source_pages": [58],
    "confidence": "high"
  },
  "dispute_resolution": {
    "method": "Arbitration in Minneapolis, MN (except certain claims)",
    "litigation_forum": "Federal District Court for District of Minnesota or Hennepin County District Court, Minneapolis",
    "governing_law": "Law of state where authorized location is situated",
    "state_overrides": "Multiple state addenda modify dispute resolution (CA, IL, MD, MN, ND, WA)",
    "source_section": "Item 17, State Addenda",
    "source_pages": [59, 85, 88, 90, 91],
    "confidence": "high"
  },
  "item_19": {
    "fpr_provided": true,
    "schedule_a": {
      "population": "Newly constructed freestanding restaurants, opened Jan 2014–Dec 2023, all 12 months reported, franchisee-owned",
      "excludes": "Texas DQ, conversions, fuel centers, non-traditional, territory operator subfranchised",
      "latest_year": 2024,
      "latest_count": 321,
      "latest_average_gross_sales": 1427281,
      "latest_median_gross_sales": 1355422,
      "latest_high": 3381809,
      "latest_low": 583730,
      "pct_at_or_above_average": 44
    },
    "schedule_b": {
      "latest_year": 2024,
      "latest_count": 55,
      "avg_cogs_pct": 30.69,
      "avg_labor_pct": 30.28,
      "avg_controllables_pct": 10.11,
      "avg_manageable_profit_pct": 28.92,
      "manageable_profit_definition": "Gross Sales minus COGS, Labor, and Restaurant Controllables. BEFORE occupancy, insurance, royalties, sales promotion fees, legal, accounting, admin.",
      "sample_limitation": "2024 has only 55 usable P&Ls (285 excluded from 321 qualifying restaurants)"
    },
    "source_section": "Item 19",
    "source_pages": [62, 63, 64, 65, 66, 67, 68],
    "confidence": "high"
  },
  "item_20_trajectory": {
    "direct_licensed_gc": {
      "2022": {"start": 1952, "opened": 38, "terminated": 25, "end": 1965, "net": 13},
      "2023": {"start": 1965, "opened": 41, "terminated": 39, "end": 1967, "net": 2},
      "2024": {"start": 1967, "opened": 30, "terminated": 28, "end": 1969, "net": 2}
    },
    "transfers": {"2022": 108, "2023": 101, "2024": 113},
    "projected_new_franchised_next_year": 38,
    "signed_not_open": 26,
    "source_section": "Item 20",
    "source_pages": [69, 72, 75, 76],
    "confidence": "high"
  },
  "item_21_financials": {
    "entity": "International Dairy Queen, Inc. (consolidated)",
    "auditor": "Deloitte & Touche LLP",
    "opinion": "Clean/unqualified",
    "opinion_date": "February 7, 2025",
    "guarantee": "IDQ unconditionally guarantees ADQ's obligations to franchisees",
    "total_assets_2024": 355906000,
    "total_liabilities_2024": 275596000,
    "stockholders_equity_2024": 80310000,
    "total_revenue_2024": 257641000,
    "net_income_2024": 97875000,
    "dividends_2024": 110000000,
    "retained_deficit_2024": -68411000,
    "cash_from_operations_2024": 105613000,
    "source_section": "Item 21, Exhibit L",
    "source_pages": [83, 491, 493, 494, 495, 496],
    "confidence": "high"
  },
  "litigation_summary": {
    "pending_count": 4,
    "concluded_count": 4,
    "notable_pending": [
      "Project Lonestar v. ADQ (N.D. Texas): breach of contract/fraud re transfer process",
      "D'Elia named in Domino's securities class action (ADQ not a party)",
      "ADQ v. Estate of Ridl (MN): termination for abandonment",
      "Oshlo-Wilkinson v. ADQ (Iowa): territory transfer dispute"
    ],
    "source_section": "Item 3",
    "source_pages": [17, 18, 19, 20],
    "confidence": "high"
  },
  "bankruptcy": {
    "disclosed": false,
    "source_section": "Item 4",
    "source_pages": [20],
    "confidence": "high"
  },
  "financing": {
    "franchisor_offers": false,
    "notes": "ADQ does not offer financing. May arrange introductions to third-party lenders.",
    "source_section": "Item 10",
    "source_pages": [38],
    "confidence": "high"
  },
  "training": {
    "total_hours": 277,
    "classroom_hours": 32,
    "ojt_hours": 245,
    "phases": 3,
    "cost_per_person": 3600,
    "required_attendees": 3,
    "location": "Phase 1-2: certified DQ location; Phase 3: Minneapolis HQ",
    "source_section": "Item 11",
    "source_pages": [46, 47, 48],
    "confidence": "high"
  },
  "technology": {
    "epos_vendor": "ParTech, Inc.",
    "initial_epos_cost": "$25,500–$33,000",
    "monthly_software_fees": "$408–$481",
    "payment_processing": "Fiserv (2%–5% per transaction + $19.95/month TransArmor)",
    "additional_monthly": "Verifone ~$10/terminal, Acumera firewall ~$51, hardware warranty $72–$150",
    "source_section": "Item 11",
    "source_pages": [44, 45],
    "confidence": "high"
  },
  "supply_chain": {
    "entity": "Unified Supply Chain, Inc. (USCI), wholly owned by IDQ",
    "margin_cap": "1.5% maximum average (permanent commitment, 2025 forward)",
    "margin_binding_on_future_buyer": true,
    "source_section": "Item 8",
    "source_pages": [34, 35],
    "confidence": "high"
  },
  "advertising_fund": {
    "allocation_2024": {"production": 19.7, "media_placement": 66.8, "admin": 4.3, "other": 9.1},
    "management_fee": "7% of sales promotion payments (not taken above 3% of gross sales)",
    "audited": true,
    "audit_type": "Independent national accounting firm annual review",
    "source_section": "Item 11",
    "source_pages": [40, 41, 42, 43],
    "confidence": "high"
  }
}
