{
  "depth_pass": "contract_burdens",
  "extraction_date": "2026-04-15",
  "source": "Exhibit A — Franchise Agreement (2025 Template)",
  "source_pages": [75, 137],
  "sections": {
    "grant_and_term": {
      "section": "1, 2",
      "grant": "Non-exclusive right to use System and operate Hotel as Brand Hotel at approved Site",
      "term": "20 years from Opening Date (new-build); conversion terms set by franchisor",
      "renewal": "None — no right to renew or extend",
      "reservation_of_rights": "Extensive — franchisor reserves right to operate competing hotels/brands inside territory",
      "existing_hotels": "Existing Brand Hotels in territory continue and may be renewed, expanded, or replaced"
    },
    "fees_and_payments": {
      "section": "3",
      "initial_franchise_fee": 50000,
      "royalty": "5.5% of GRR",
      "system_services": "4.5% of GRR",
      "payment_due": "15th of following month",
      "interest": "1.5% per month on overdue amounts",
      "taxes": "Franchisee pays any sales/use/gross receipts tax imposed on franchisor for payments received",
      "efts": "Franchisor may require electronic funds transfer/direct debit"
    },
    "site_and_construction": {
      "section": "4",
      "site_approval": "Franchisor review within 60 days; deemed disapproved if no approval within 60 days",
      "construction_site_visits": "Up to 3 (pre-drywall, post-millwork, final)",
      "tech_site_visits": "Up to 2 (during construction, post-installation)",
      "auto_extensions": "90-day rolling extensions unless franchisor provides 30 days notice",
      "extension_fee": "Then-current fee ($5,000)",
      "pre_opening_inspection": "Within 30 days of readiness notice; at franchisee cost",
      "unauthorized_opening_penalty": "$5,000/day plus costs",
      "comfort_letter": "Available at $2,000; first may be free",
      "room_addition_fee": "$500/room",
      "maintenance_obligation": "Hotel refurbishment at franchisor's direction; $500/month non-compliance fee for tech standards"
    },
    "franchisee_responsibilities": {
      "section": "5",
      "management": "Franchisee or approved Management Company must manage; GM required full-time",
      "gm_certification": "Must complete GM Certification before opening or within 60 days",
      "staffing": "Franchisee hires, fires, supervises all employees; independent contractor",
      "systems": "Must purchase/license franchisor-approved PMS, RMS, CRS and maintain current versions",
      "reservation_service": "Must participate in and honor all confirmed reservations; give first priority",
      "loyalty_programs": "Must participate in all required loyalty/discount/promotional programs",
      "pricing": "Franchisee sets own rates but must honor all reservations and listed rates",
      "24_7_operation": "Must operate 24/7",
      "no_diverting": "Cannot divert business to non-Brand Hotels",
      "landlord_provisions": "Lease must contain franchisor-required provisions",
      "advertising_approval": "All Marketing Materials using Marks must be pre-approved; deemed disapproved if no response in 10 business days",
      "guest_complaints": "Must satisfactorily address within 72 hours or face $150 fee + guest compensation",
      "data_ownership": "All Data and Guest Data owned by franchisor; franchisee has non-exclusive use right during term",
      "no_timeshare": "Cannot conduct timeshare/vacation ownership without consent",
      "no_competing_business": "Cannot promote competing lodging facility without approval"
    },
    "franchisor_rights": {
      "section": "6",
      "inspection": "May inspect Hotel and operations, books, records at any time without notice",
      "training": "May require initial, periodic, remedial training at franchisee cost",
      "consultation": "May (but not required to) provide consultation and advice",
      "quality_assurance": "May conduct QA audits; failure triggers remedial training ($4,000-$6,500) and/or re-inspection ($1,000)",
      "delegation": "May delegate all obligations to affiliates, agents, or contractors"
    },
    "system_and_standards": {
      "section": "7",
      "modifications": "Franchisor may modify, amend, supplement System and Standards at any time, including material changes, at sole discretion",
      "standards_access": "Digital/electronic access during term; 128-page manual",
      "no_limit_on_changes": "No contractual limitation on frequency or scope of Standards changes"
    },
    "marks": {
      "section": "9",
      "ownership": "All goodwill and ownership rights accrue to franchisor",
      "modification": "Franchisor may change/discontinue/substitute Marks at any time without liability",
      "franchisee_expense": "Implementation of mark changes at franchisee expense",
      "no_compensation": "No compensation for mark changes"
    },
    "records_and_audits": {
      "section": "10",
      "books_maintenance": "Must maintain books and records per franchisor requirements",
      "accounting_statements": "Must submit financial reports as required",
      "audit_rights": "Franchisor may audit at any time; franchisee pays audit costs if deficiency found or accounting procedures deficient",
      "lender_information": "Must provide lender information as requested"
    },
    "insurance": {
      "section": "11",
      "gl_minimum": 10000000,
      "auto_minimum": 10000000,
      "workers_comp": "Per state requirements",
      "employer_liability": 5000000,
      "property": "Full replacement cost",
      "bi_coverage": "12 months lost profits including fees to franchisor",
      "earthquake_flood": "75% replacement cost if in hazard area",
      "terrorism": "Full replacement cost plus lost profits",
      "cyber": 3000000,
      "epl": 1000000,
      "boiler_machinery": "Full replacement of damaged items plus lost profits",
      "crime": "Commensurate with risk",
      "insurer_rating": "A.M. Best A-/VII minimum",
      "franchisor_as_insured": "Must name franchisor as additional insured",
      "failure_to_maintain": "Franchisor may obtain at franchisee's cost plus procurement penalty"
    },
    "data_privacy": {
      "section": "12",
      "data_ownership": "Franchisor owns all Data and Guest Data",
      "franchisee_use": "Non-exclusive during term for hotel operation and marketing franchisor products",
      "no_sale": "Cannot sell, transfer, or use data for non-hotel purposes",
      "privacy_policy": "Cannot publish/revise privacy policy without franchisor consent",
      "breach_notification": "Must immediately notify franchisor of data loss/theft/compromise",
      "indemnification": "Must indemnify franchisor for data loss or privacy law non-compliance"
    },
    "condemnation_casualty": {
      "section": "13",
      "condemnation": "Agreement terminates; franchisor entitled to fair portion of condemnation award for lost revenue",
      "casualty": "If exceeds coverage limits, either party may terminate. Franchisor entitled to portion of insurance proceeds for lost revenue.",
      "termination_fee_waiver": "Available if: sign termination agreement including release, hotel no longer used as lodging, pay all accrued amounts, comply with post-termination obligations"
    },
    "transfer": {
      "section": "14",
      "franchisor_transfer": "No restrictions on franchisor's right to assign",
      "franchisee_transfer": "Requires franchisor approval for all transfers",
      "transfer_conditions": [
        "Satisfy all monetary obligations",
        "Pay then-current PIP fee",
        "Transferee updates hotel to then-current Standards",
        "Franchisee and owners sign general release",
        "Transferee submits new application",
        "Transferee pays then-current IFF as transfer fee",
        "Transferee enters then-current FA (may be materially different)",
        "Transferee meets ownership criteria"
      ],
      "death_transfer": "Must transfer within required timeframe meeting all conditions; failure may result in termination",
      "securities_offerings": "Must pay third-party review costs",
      "mortgages": "Permitted with franchisor notification requirements",
      "non_control_changes": "Notice required but not consent; assumption fee $1,500-$5,000"
    },
    "termination": {
      "section": "15",
      "curable_defaults": {
        "cure_period": "30 days (10 for monetary)",
        "examples": "Non-compliance with Standards, failure to pay fees, failure to maintain insurance"
      },
      "immediate_termination": {
        "triggers": [
          "Liquidation, dissolution, or action to liquidate/dissolve",
          "Bankruptcy petition filed by or against franchisee",
          "Cease operating under Brand or lose possession of Hotel",
          "Hotel or assets attached",
          "Contest franchisor's ownership of Marks",
          "Fail to identify Hotel as Brand Hotel or violate proprietary rights",
          "Unauthorized use of Marks or Confidential Information",
          "Breach insurance, indemnification, data privacy provisions or safety/security Standards",
          "Felony conviction of franchisee or owners",
          "False records submitted",
          "Action adversely reflecting on System",
          "Hotel construction/renovation threatens public safety",
          "3 defaults in any 12-month period",
          "2 similar defaults in any 6-month period"
        ]
      },
      "suspension": "Franchisor may suspend reservation service, website listing, loyalty programs, and other services as interim remedy"
    },
    "post_termination": {
      "section": "16",
      "de_identification": "Cease all Brand use; remove all Marks; change phone/web/listings; allow franchisor inspection",
      "pay_amounts_owed": "Within 10 days after termination or expiration",
      "liquidated_damages": "Within 10 days; tiered formula based on timing",
      "actual_damages": "Franchisor may seek actual damages and attorney fees in lieu of or in addition to LD under certain circumstances",
      "survival": "Indemnification, confidentiality, noncompete, dispute resolution provisions survive"
    },
    "indemnification": {
      "section": "17",
      "scope": "Broad — covers all liabilities, fines, penalties, damages arising from franchisee, Hotel, Site, or Agreement",
      "includes_negligence": "Yes — even if caused by franchisor's negligence",
      "defense_obligation": "Must defend and reimburse upon demand; franchisor may control defense at franchisee cost",
      "settlement_right": "Franchisor may settle any claim at franchisee cost",
      "limitation_of_liability": "Franchisor has no liability for obligations arising from Agreement or franchisee-franchisor relationship — waiver of vicarious liability claims",
      "survival": "Survives termination/expiration",
      "no_mitigation_required": "Franchisor not required to seek recovery from third parties or mitigate losses"
    },
    "dispute_resolution": {
      "section": "19",
      "governing_law": "North Carolina (subject to state addenda)",
      "arbitration": "All disputes except indemnification, equitable relief, and enforcement of arbitral awards",
      "arbitration_venue": "Charlotte, NC (franchisor HQ)",
      "injunctive_relief": "Franchisor may seek in any court of competent jurisdiction without posting bond",
      "waivers": {
        "punitive_damages": "Waived",
        "jury_trial": "Waived",
        "class_actions": "Waived — must pursue individually"
      },
      "jurisdiction": "Non-exclusive jurisdiction of North Carolina courts for non-arbitrable disputes",
      "one_year_notice": "Franchisee must notify franchisor of alleged breach within 1 year or claim is waived"
    },
    "force_majeure": {
      "section": "20.4",
      "applies_to": "Franchisor's performance obligations only — extended for period of delay",
      "franchisee_obligation": "May be required to close/cease operations during Force Majeure event at franchisor's direction",
      "reopening": "Requires franchisor approval of franchisee certification"
    },
    "guaranty": {
      "exhibit": "J",
      "scope": "Personal guaranty of franchisee's obligations by principal owners",
      "hotel_owner_guaranty": "If hotel owned by different entity than franchisee, hotel owner must sign guaranty",
      "unlimited": "Appears to be unlimited personal guaranty"
    }
  },
  "distinctive_clauses": [
    "No noncompete during or post-term — unusually favorable",
    "No renewal right — unusual for hotel franchise",
    "Franchisor owns all Data and Guest Data — broad data ownership",
    "1-year claim notification requirement — franchisee must notify of alleged breach within 1 year or claim waived",
    "Class action waiver — must pursue disputes individually",
    "Punitive damages waiver",
    "Franchisor's indemnification includes franchisee's negligence claims — very broad",
    "Force Majeure extends only franchisor's obligations, not franchisee's",
    "Franchisor may modify System/Standards at any time without limit",
    "Technology non-compliance penalty of $500/month"
  ]
}
