{
  "depth_pass": "A2_narrative_to_canonical_promotion",
  "promoted_facts": [
    {"fact": "DPD optional profit-sharing plan: 10-year purchase commitment for share of DPD center profits", "source": "Reader report Pass C / Item 8 p.39", "promoted_to": "item8_supplier_restrictions.profit_sharing"},
    {"fact": "Coca-Cola exclusive beverage through December 31, 2030 with volume incentive funding", "source": "Reader report Pass C / Item 8 p.37", "promoted_to": "item8_supplier_restrictions.beverage"},
    {"fact": "DNAF received $25.3M and DPL received $6.7M from vendor marketing agreements in 2024", "source": "Reader report Pass C / Item 8 p.39", "promoted_to": "item6_advertising"},
    {"fact": "Franchise candidate validity: 1 year after completing FMS training", "source": "Reader report Pass C / Item 11 p.51", "promoted_to": "item11_training"},
    {"fact": "Non-compete during term: ANY similar business ANYWHERE (unusually broad geographic scope)", "source": "Reader report Pass E / Item 17 p.62", "promoted_to": "item17_noncompete"},
    {"fact": "Purchase option formula: percentage of Royalty Sales during prior 12 months less deductions; 10% at closing + 60 monthly installments at prime rate", "source": "FA Section 19 p.365", "promoted_to": "item17_termination"},
    {"fact": "2018 7.5yr Notes ($403M) and 2015 10yr Notes ($742M) = $1.145B anticipated repayment October 2025 — material refinancing event", "source": "DPF Note 3 p.297, DPL Note 2 p.316", "promoted_to": "item21_financial_statements"},
    {"fact": "DPL distributions: $550.6M (2024), $444.2M (2023), $462.0M (2022) — consistently above net income", "source": "DPL Statement of Member's Deficit p.306", "promoted_to": "item21_financial_statements"},
    {"fact": "DPL equity-based compensation: $43.3M (2024), 458K stock options outstanding at avg $306.85", "source": "DPL Note 8 p.325", "promoted_to": "item21_structural_facts"},
    {"fact": "DPL lease expense: $91.2M total rent (2024); finance lease obligations: $66.1M", "source": "DPL Note 4 p.320", "promoted_to": "item21_structural_facts"}
  ],
  "total_promoted": 10
}
