{
  "document_identity": {
    "filing_id": "638047-2025",
    "brand": "ProColor Collision",
    "franchisor_legal_name": "ProColor Collision USA LLC",
    "franchisor_state_of_formation": "Delaware",
    "franchisor_formation_date": "2020-04-23",
    "principal_address": "650 Pelham Boulevard, Suite 100, St. Paul, Minnesota 55114",
    "phone": "952-944-8000",
    "website": "www.ProColorUSA.com",
    "issuance_date": "2025-03-29",
    "fiscal_year_end": "December 31",
    "state_filed": "Wisconsin",
    "source_section": "Cover page, Item 1",
    "source_pages": [1, 8],
    "confidence": "high"
  },
  "parent_structure": {
    "immediate_parent": "Mondofix USA LLC",
    "ultimate_parent": "Mondofix Inc.",
    "ultimate_parent_jurisdiction": "Canada",
    "ultimate_parent_address": "99 Émilien Marcoux, Suite 101, Blainville, Quebec, J7C 0B4, Canada",
    "predecessor": "Mondofix Inc. (provided concepts, trade secrets, IP)",
    "key_affiliates": [
      {"name": "Carrossier ProColor", "locations": 157, "geography": "Canada", "type": "collision repair"},
      {"name": "Fix Auto", "locations": 654, "geography": "worldwide", "type": "collision repair"},
      {"name": "Novus Glass", "locations_us": 155, "type": "glass repair"},
      {"name": "Fix Auto US (79411 USA Inc.)", "locations_us": "unaffiliated master franchisee", "type": "collision repair"}
    ],
    "source_section": "Item 1",
    "source_pages": [8, 9, 10, 11],
    "confidence": "high"
  },
  "franchise_type": {
    "description": "Full-service auto collision repair facility",
    "services": "Automotive repair and replacement, appraisal, insurance billing, repair, after-care warranty under National Warranty Program",
    "began_franchising": "2020-07",
    "preferred_model": "Conversion of existing auto repair facility; also new builds",
    "source_section": "Cover page, Item 1",
    "source_pages": [1, 8, 9],
    "confidence": "high"
  },
  "system_size": {
    "total_units_end_2024": 30,
    "franchised_units_end_2024": 30,
    "company_owned_units_end_2024": 0,
    "states_present": ["California", "Montana", "North Carolina", "Texas"],
    "units_by_state": {"California": 24, "Texas": 4, "Montana": 1, "North Carolina": 1},
    "projected_new_franchised_2025": 27,
    "projected_new_company_owned_2025": 1,
    "franchise_agreements_signed_not_opened": 9,
    "growth_trajectory": {"2022": {"start": 6, "end": 10}, "2023": {"start": 10, "end": 19}, "2024": {"start": 19, "end": 30}},
    "terminations": {"2022": 3, "2023": 1, "2024": 2, "total": 6},
    "transfers": {"2024": 1},
    "source_section": "Item 20",
    "source_pages": [57, 58, 59, 60],
    "confidence": "high"
  },
  "fees": {
    "initial_franchise_fee": {
      "standard": 20000,
      "reduced": 10000,
      "reduced_conditions": "Existing franchisee in good standing purchasing additional franchise, or multiple simultaneous purchases",
      "refundable": false,
      "source_section": "Item 5",
      "source_pages": [15],
      "confidence": "high"
    },
    "royalty": {
      "new_location": {
        "rate": "Greater of $2,000/month or 3% of Gross Sales",
        "type": "percentage_with_minimum"
      },
      "conversion": {
        "base_fee": "Greater of $2,000 or 1.5% of Monthly Base Volume",
        "growth_royalty": "3% of monthly Gross Sales exceeding Monthly Base Volume",
        "base_volume_definition": "Average annual Gross Sales for 3 years before signing / 12",
        "type": "split_base_growth"
      },
      "payment_timing": "15th of each month for prior month",
      "source_section": "Item 6, Note 1",
      "source_pages": [16, 19, 20],
      "confidence": "high"
    },
    "marketing_fund": {
      "rate": "0.75% of Gross Sales",
      "maximum_rate": "1% with majority approval of all US ProColor locations",
      "payment_timing": "15th of each month",
      "2024_spending_breakdown": {
        "advertising_placements": "65.8%",
        "trade_shows_events": "27.8%",
        "general_administration": "3.7%",
        "reputation_management": "1.6%",
        "social_media": "0.8%",
        "online_marketing_support": "0.3%"
      },
      "audited": false,
      "source_section": "Item 6, Item 11",
      "source_pages": [16, 20, 38, 39],
      "confidence": "high"
    },
    "renewal_fee": 5000,
    "transfer_fee": 10000,
    "technology_fees": {
      "ccc_one_setup": "$3,395 (≤5 users) or $4,395 (6+ users)",
      "ccc_one_monthly": "$1,200 + $110/additional user",
      "ccc_one_min_term_months": 36,
      "insurance_mailboxes": "$160/month (3-5) or $215/month (6+)",
      "central_review": "$155/month",
      "engage": "$255/month",
      "email": "$6.30-$9.18/month per account (min 1 required)"
    },
    "alternative_supplier_fee": {
      "paint_vendor": "1.6% of Gross Sales",
      "parts_noncompliance": "1% of Gross Sales",
      "maximum_combined": "2.6% of Gross Sales",
      "parts_threshold": "85% of total OEM/aftermarket/recycled parts from designated suppliers"
    },
    "convention_fee": {
      "amount": "$1,000-$1,500 per person",
      "frequency": "2 per year",
      "mandatory_payment": true
    },
    "other_fees": {
      "promotional_inventory": "Up to $50/month",
      "audit": "Cost of audit (if understatement ≥2%)",
      "interest_on_late_payments": "Lesser of 1.5%/month or legal max",
      "late_report_fee": "$200 (subject to 25% annual increase)",
      "insurers_account_deposit_on_termination": "$15,000 retained for 18 months"
    },
    "source_section": "Items 5, 6",
    "source_pages": [15, 16, 17, 18, 19, 20, 21],
    "confidence": "high"
  },
  "initial_investment": {
    "conversion": {
      "low": 38300,
      "high": 199500,
      "includes_franchise_fee_low": 10000,
      "includes_franchise_fee_high": 20000
    },
    "new_build": {
      "low": 316800,
      "high": 3129500,
      "includes_franchise_fee_low": 10000,
      "includes_franchise_fee_high": 20000
    },
    "facility_specs": {
      "production_sqft": "10,000-15,000",
      "parking_yard_sqft": "20,000-30,000",
      "office_sqft": "2,000-5,000"
    },
    "source_section": "Item 7",
    "source_pages": [22, 23, 24, 25],
    "confidence": "high"
  },
  "territory": {
    "type": "designated_non_exclusive",
    "definition_method": "Zip code(s) based on 25% of available collision spend capacity using mapping software",
    "exclusivity": "Franchisor will not operate or grant ProColor Collision rights within Territory while franchisee compliant",
    "carve_outs": [
      "Insurance/fleet/national account servicing failure",
      "Other brands (Fix Auto, Novus) may operate inside Territory",
      "M&A activity — acquired brands may operate inside Territory",
      "Capacity overflow provision (30-day respond or lose exclusivity)"
    ],
    "no_options_or_rofr_for_additional": true,
    "relocation": "Requires consent, within Territory only",
    "source_section": "Item 12",
    "source_pages": [42, 43, 44],
    "confidence": "high"
  },
  "term_and_renewal": {
    "initial_term_years": 5,
    "renewal_terms": 2,
    "renewal_term_years": 5,
    "max_total_years": 15,
    "renewal_notice_window": "210-270 days before expiration",
    "renewal_conditions": [
      "Sign new franchise agreement (may have materially different terms)",
      "Pay $5,000 renewal fee",
      "Execute general release (subject to state law)",
      "Complete refresher training",
      "Remodel to current standards and specifications",
      "Not in default"
    ],
    "materially_different_terms_risk": true,
    "source_section": "Item 17, FA Section 5",
    "source_pages": [51, 52, 122],
    "confidence": "high"
  },
  "termination": {
    "by_franchisee": "Not applicable (no voluntary termination right)",
    "by_franchisor_without_cause": "Not applicable",
    "by_franchisor_with_cause": true,
    "curable_defaults_cure_period_days": 30,
    "monetary_default_cure_period_days": 5,
    "non_curable_defaults": [
      "Bankruptcy/insolvency/assignment for creditors",
      "Liquidation or abandonment",
      "Loss of premises or lease breach",
      "Gross Sales understatement 2+ times in 12 months",
      "Criminal act or indictable offense adversely affecting goodwill",
      "Disqualification from insurance work",
      "Unsatisfied judgment",
      "In-term noncompete violation",
      "Default under any other agreement with franchisor"
    ],
    "death_disability": "Not addressed in Item 17",
    "holdover_clause": "Operation after term expiration is at-will, terminable by franchisor on 30 days notice",
    "source_section": "Item 17, FA Sections 25, 5.3",
    "source_pages": [51, 52, 122, 123],
    "confidence": "high"
  },
  "transfer": {
    "franchisor_approval_required": true,
    "right_of_first_refusal": true,
    "transfer_fee": 10000,
    "conditions": [
      "Transferee meets requirements",
      "Sign new FA for remaining term (may have different fees/territory)",
      "No new initial franchise fee for transferee",
      "Sign release (subject to state law)",
      "Appoint franchisor as attorney-in-fact for CCC ONE transfer"
    ],
    "source_section": "Item 17, FA Sections 23-24",
    "source_pages": [52, 53],
    "confidence": "high"
  },
  "noncompete": {
    "during_term": {
      "applies": true,
      "scope": "No involvement in collision repair or franchise system/banner/chain related to car collision industry",
      "subject_to_state_law": true
    },
    "post_term": {
      "applies": false,
      "notes": "Item 17 explicitly states 'Not applicable' for post-term noncompete"
    },
    "source_section": "Item 17, FA Section 22",
    "source_pages": [53, 54],
    "confidence": "high"
  },
  "dispute_resolution": {
    "method": "Mediation first, then arbitration",
    "mediation_location": "Location selected by mediator",
    "arbitration_location": "Minneapolis, Minnesota",
    "governing_law": "Minnesota",
    "subject_to_state_overrides": true,
    "source_section": "Item 17, FA Section 28",
    "source_pages": [54],
    "confidence": "high"
  },
  "training": {
    "initial": {
      "duration_days": "3-4",
      "classroom_hours": "9.5-10",
      "ojt_hours": "8.5-10.5",
      "total_hours": "18-20.5",
      "location": "Minnesota HQ, online, or franchisee location",
      "fee": "None",
      "travel_at_franchisee_expense": true,
      "completion_deadline_days": 60,
      "failure_consequence": "Termination, no refund"
    },
    "ongoing": {
      "mandatory_training_available": true,
      "convention_attendance_required": true,
      "convention_fee": "$1,000-$1,500/person",
      "additional_training_fee": "$200-$300/day/trainer + travel"
    },
    "source_section": "Item 11",
    "source_pages": [34, 35, 36],
    "confidence": "high"
  },
  "operations_manuals": {
    "total_manuals": 4,
    "manuals": [
      {"name": "ProColor Operations Guide", "pages": 239, "chapters": 14},
      {"name": "ProColor Brand Standards", "pages": 56, "chapters": 7},
      {"name": "ProColor-CCC Integration Guide", "pages": 9, "chapters": 7},
      {"name": "Onboarding & Franchise Support Guide", "pages": 82}
    ],
    "total_pages": 386,
    "source_section": "Item 11, Exhibit C",
    "source_pages": [33, 82, 83, 84, 85],
    "confidence": "high",
    "recovery_note": "Exhibit C pages recovered via image rendering (R1)"
  },
  "item_19": {
    "fpr_made": false,
    "tables": [],
    "narrative": "No financial performance representations made.",
    "source_section": "Item 19",
    "source_pages": [56],
    "confidence": "high"
  },
  "item_21_financial_health": {
    "auditor": "Ernst & Young",
    "opinion": "Unqualified (clean)",
    "fiscal_years_audited": ["2024", "2023", "2022"],
    "revenue": {
      "2024": {"royalties": 1176336, "vendor_allowances": 641444, "franchisee_contributions": 553777, "sublease": 199579, "total": 2571136},
      "2023": {"royalties": 692720, "vendor_allowances": 480878, "franchisee_contributions": 213038, "total": 1386636},
      "2022": {"royalties": 311725, "vendor_allowances": 171226, "franchisee_contributions": 24333, "total": 507284}
    },
    "net_loss": {"2024": -1896, "2023": -661258, "2022": -1336617},
    "cumulative_deficit": -4171334,
    "parent_investment": 4825100,
    "balance_sheet_2024": {
      "total_assets": 2847361,
      "total_liabilities": 2193595,
      "net_membership_interest": 653766,
      "cash": 619337,
      "accounts_receivable_net": 672385,
      "right_of_use_asset": 802948,
      "advances_to_parent": 426975,
      "deferred_revenue_total": 843969,
      "lease_liabilities_total": 802948
    },
    "going_concern": {
      "2023": "Explicit going concern discussion — dependent on parent company support",
      "2024": "Going concern language removed from 2024 financial statements"
    },
    "key_observations": [
      "Revenue quintupled in 2 years ($507K→$2.57M)",
      "Loss nearly eliminated in 2024 ($1,896 net loss)",
      "Still carrying $4.17M cumulative deficit",
      "Parent has invested $4.83M since inception with no new capital in 2024",
      "$427K in advances to parent company — cash flowing upstream",
      "Operating cash outflow of $324K in 2024 (improved from $365K in 2023)",
      "AR aging: $84.8K past 91 days with unchanged $51.7K allowance",
      "Deferred revenue $844K — initial fees being recognized over license term"
    ],
    "source_section": "Item 21, Exhibit E",
    "source_pages": [90, 91, 92, 93, 94, 95, 96, 97, 98, 99, 100, 101, 102, 103, 104, 105, 106, 107, 108, 109, 110, 111, 112, 113, 114, 115, 116],
    "confidence": "high"
  },
  "litigation": {
    "procolor_specific": 0,
    "related_party_matters": [
      {"parties": "79411 USA Inc. v. Mondofix", "year_filed": 2017, "status": "Resolved 2020", "summary": "Fix Auto master license renewal dispute"},
      {"parties": "Automotive Aftermarket Franchises v. Mondofix", "year_filed": 2020, "jurisdiction": "Ireland", "status": "Settled Oct 2021", "summary": "Termination dispute"}
    ],
    "lawsuits_against_franchisees_2024": 0,
    "source_section": "Item 3",
    "source_pages": [13],
    "confidence": "high"
  },
  "bankruptcy": {
    "disclosed": false,
    "source_section": "Item 4",
    "source_pages": [14],
    "confidence": "high"
  },
  "special_risks": [
    {"risk": "Out-of-state dispute resolution", "detail": "Mediation/arbitration/litigation in Minnesota"},
    {"risk": "Short operating history", "detail": "Franchisor at early stage of development, began franchising July 2020"},
    {"risk": "Mandatory minimum payments", "detail": "Conversions must make mandatory minimum royalty payments regardless of sales levels"}
  ],
  "state_addenda": {
    "states": ["California", "Hawaii", "Illinois", "Minnesota", "New York", "Wisconsin"],
    "material_overrides": {
      "California": ["Release restrictions under Corp. Code §31512", "Arbitration venue enforceability concern", "Max interest 10%", "Bankruptcy termination may not be enforceable under 11 USC §101", "No waiver of franchise law claims"],
      "Hawaii": ["7-day FDD delivery before signing", "Filing not endorsement"],
      "Illinois": ["Forum/venue outside IL void for IL-enforceable actions", "IL franchise law governs termination/non-renewal rights"],
      "Minnesota": ["90-day termination notice with 60-day cure", "180-day non-renewal notice", "No general release permitted (Rule 2860.4400D)", "No injunctive relief consent", "No jury trial waiver or liquidated damages"],
      "New York": ["GBL Article 33 protections preserved", "Franchisor assignment requires good faith and financial ability", "No waiver of franchise law claims", "10 business day FDD delivery"],
      "Wisconsin": ["Fair Dealership Law supersedes inconsistent FA provisions", "90-day notice of termination/non-renewal with 60-day cure"]
    },
    "source_section": "Exhibit A",
    "source_pages": [64, 65, 66, 67, 68, 69, 70, 71, 72, 73, 74, 75],
    "confidence": "high"
  },
  "insurance_requirements": {
    "general_liability": "$1,000,000 per occurrence / $2,000,000 aggregate",
    "garage_keepers": "$2,000,000 aggregate (direct primary, full vehicle value)",
    "vehicle": "$1,000,000 bodily injury/property/death + comprehensive/collision ($1,000 deductible) + GAP",
    "property_fire": "Replacement value + improvements",
    "umbrella": "$1,000,000",
    "workers_comp": "$1,000,000 per employee/aggregate/accident",
    "environmental": "$1,000,000 per claim and aggregate",
    "source_section": "Item 8",
    "source_pages": [26, 27, 28],
    "confidence": "high"
  },
  "key_contract_provisions": {
    "modification_by_supermajority": "80% of ProColor Collision Centers can bind all franchisees to FA modifications",
    "franchisor_assignment": "No restriction on franchisor's right to assign",
    "electronic_data_access": "Franchisor can independently access all electronic information and data without compensation",
    "opening_deadlines": {
      "conversion": "90 days from signing",
      "new_build": "180 days from signing",
      "failure_consequence": "Termination, all amounts retained"
    },
    "ip_assignment": "All IP improvements/suggestions automatically assigned to franchisor without compensation (FA Section 9.6)",
    "no_subcontracting": "Cannot sub-contract services except to other ProColor franchisees (FA Section 12.3)",
    "insurers_account_insurance": "Franchisor maintains theft/fraud insurance on Insurers Account benefiting franchisees (FA Section 10.3)",
    "record_retention_years": 6,
    "no_withholding": "Franchisee may not withhold payments on grounds of franchisor non-performance (FA Section 29.13)",
    "supplier_benefit_retention": "Franchisor retains ALL supplier discounts, rebates, commissions, and entitled to markup/profit on sales to franchisee (FA Section 13.4)",
    "source_section": "Item 17, FA Sections 29.8, 23, 14, 9.6, 12.3, 10.3, 29.13, 13.4",
    "source_pages": [54, 33, 37, 126, 127, 129, 131, 155],
    "confidence": "high"
  },
  "unresolveds": [
    {
      "id": "U1",
      "description": "Termination rates in early years: 3 terminations in 2022 out of 10 end-of-year units (30% rate). Reasons not disclosed.",
      "severity": "medium",
      "source": "Item 20, page 58"
    },
    {
      "id": "U2",
      "description": "Fix Auto US conflict resolution: No policy for resolving conflicts between ProColor and Fix Auto franchisees, despite common parent ownership (Mondofix).",
      "severity": "medium",
      "source": "Item 12, pages 43-44"
    },
    {
      "id": "U3",
      "description": "Insurance company volume rebate terms: Described as 'typically 1-5%' but 'can be greater.' Specific terms undisclosed.",
      "severity": "low",
      "source": "Item 6 Note 7, page 21"
    },
    {
      "id": "U4",
      "description": "80% supermajority modification rule: Any FA modification accepted by 80% of ProColor locations is binding on all. In a 30-unit system, 24 franchisees control outcome.",
      "severity": "medium",
      "source": "Item 17, FA Section 29.8, page 155"
    },
    {
      "id": "U5",
      "description": "Advances to parent company: $427K non-interest-bearing advances to parent, not repayable before Jan 1, 2026. Cash flowing upstream while entity is cash-flow negative.",
      "severity": "medium",
      "source": "Exhibit E, pages 94, 101"
    }
  ],
  "contradictions": [
    {
      "id": "C1",
      "description": "Item 20 Table 4 (Company-Owned) Total rows show years 2021, 2022, 2023 instead of 2022, 2023, 2024. Data (all zeros) is consistent regardless.",
      "items_involved": ["Item 20"],
      "resolution_status": "Not material — typographic error, data consistent"
    }
  ],
  "state_addenda_overrides": {
    "states_with_addenda": ["California", "Hawaii", "Illinois", "Minnesota", "New York", "Wisconsin"],
    "California": {
      "forum_selection": "Minnesota forum/law may not be enforceable under California law",
      "general_release": "Cannot waive franchise law claims under Corp. Code §31512",
      "interest_rate": "Capped at 10% (vs. 18% in FA)",
      "termination": "Bankruptcy termination may not be enforceable; CFRA provides additional transfer/termination/non-renewal rights",
      "anti_waiver": "No waiver of franchise law claims; no disclaimer of franchisor representations"
    },
    "Hawaii": {
      "anti_waiver": "No waiver of franchise law claims including fraud in the inducement"
    },
    "Illinois": {
      "forum_selection": "Forum/venue outside IL void for IL-enforceable actions (arbitration outside IL still permitted)",
      "governing_law": "IL law governs to extent required by Rule 200.608",
      "termination": "Rights affected by 815 ILCS 705/19 and 705/20",
      "anti_waiver": "Cannot waive IL Franchise Disclosure Act compliance"
    },
    "Minnesota": {
      "notice_cure": "90-day termination notice with 60-day cure; 180-day non-renewal notice",
      "general_release": "Prohibited (Rule 2860.4400D)",
      "damages": "No jury trial waiver, liquidated damages, termination penalties, or judgment notes",
      "termination": "Transfer not unreasonably withheld; injunctive relief requires court determination",
      "noncompete": "Franchisor must protect trademark rights or indemnify"
    },
    "New_York": {
      "general_release": "GBL Article 33 rights preserved at renewal/transfer",
      "termination": "Franchisee may terminate on any grounds available by law",
      "governing_law": "Choice of law cannot waive GBL Article 33 rights",
      "anti_waiver": "No waiver of franchise law claims; supersedes all other document terms"
    },
    "Wisconsin": {
      "termination": "Fair Dealership Law: no termination/non-renewal without good cause; 90-day notice; 60-day cure"
    },
    "summary_matrix": {
      "forum_selection": ["California", "Illinois"],
      "governing_law": ["California", "Illinois", "New York"],
      "general_release": ["California", "Minnesota", "New York"],
      "notice_cure": ["Minnesota", "Wisconsin"],
      "termination": ["California", "Illinois", "Minnesota", "New York", "Wisconsin"],
      "interest_rate": ["California"],
      "damages": ["Minnesota"],
      "noncompete": ["Minnesota"],
      "anti_waiver": ["California", "Hawaii", "Illinois", "New York"]
    },
    "source_section": "Exhibit A",
    "source_pages": [64, 65, 66, 67, 68, 69, 70, 71, 72, 73, 74, 75],
    "confidence": "high"
  }
}
